torchland/__init__.py
torchland/trainer.py
torchland/datasets/__init__.py
torchland/datasets/img_popular.py
torchland/datasets/img_transfer.py
torchland/datasets/loader_maker.py
torchland/datasets/mixture_gaussians.py
torchland/datasets/noisy_mnist.py
torchland/datasets/random.py
torchland/datasets/vctk.py
torchland/utils/__init__.py
torchland/utils/noise.py
torchland/utils/spectrogram.py
pytorch_land-0.1.2.dist-info/METADATA
pytorch_land-0.1.2.dist-info/WHEEL
pytorch_land-0.1.2.dist-info/top_level.txt
pytorch_land-0.1.2.dist-info/RECORD
