Metadata-Version: 2.1
Name: pytorch-land
Version: 0.1.2
Summary: pytorch-land for happy deep learning
Home-page: https://github.com/dansuh17/pytorch-land
Author: dansuh17
Author-email: kaehops@gmail.com
License: MIT
Platform: UNKNOWN
